split_pdf_by_page/__init__.py
split_pdf_by_page/cli.py
split_pdf_by_page-0.1.0.dist-info/METADATA
split_pdf_by_page-0.1.0.dist-info/WHEEL
split_pdf_by_page-0.1.0.dist-info/entry_points.txt
split_pdf_by_page-0.1.0.dist-info/RECORD
