Metadata-Version: 2.4
Name: split-pdf-by-page
Version: 0.1.0
Summary: 
Author: pavel
Author-email: mpavel@duck.com
Requires-Python: >=3.10
Classifier: Programming Language :: Python :: 3
Classifier: Programming Language :: Python :: 3.10
Classifier: Programming Language :: Python :: 3.11
Classifier: Programming Language :: Python :: 3.12
Classifier: Programming Language :: Python :: 3.13
Classifier: Programming Language :: Python :: 3.14
Requires-Dist: pycryptodome (>=3.23.0,<4.0.0)
Requires-Dist: pypdf2 (>=3.0.1,<4.0.0)
